{"user_id": 27, "config": {"maxtrix_factorization": {"steps": 10, "gamma": 0.001, "lamda": 0.02}, "worker": {"nums_workers": 3, "nums_recommendations": 10}}, "data": {"top_favorites": ["Good Will Hunting (1997)", "Schindler's List (1993)", "Mis\u00e9rables, Les (1995)", "Sixth Sense, The (1999)", "American Beauty (1999)", "Cape Fear (1991)", "Perfect Murder, A (1998)", "Eyes Wide Shut (1999)", "Hunt for Red October, The (1990)", "October Sky (1999)"], "nearest_neighbours": ["Shawshank Redemption, The (1994)", "Fugitive, The (1993)", "Blade Runner (1982)", "Terminator 2: Judgment Day (1991)", "Fargo (1996)", "Star Wars: Episode V - The Empire Strikes Back (1980)", "Raiders of the Lost Ark (Indiana Jones and the Raiders of the Lost Ark) (1981)", "Lock, Stock & Two Smoking Barrels (1998)", "Matrix, The (1999)", "Snatch (2000)"], "latent_factors": ["Heat (1995)", "Casino (1995)", "Get Shorty (1995)", "Twelve Monkeys (a.k.a. 12 Monkeys) (1995)", "Babe (1995)", "Clueless (1995)", "Usual Suspects, The (1995)", "Mighty Aphrodite (1995)", "Mr. Holland's Opus (1995)", "City Hall (1996)"]}, "timestamp": "2018-04-27 16:35:47"}