{"config": {"worker": {"nums_workers": 3, "nums_recommendations": 10}, "maxtrix_factorization": {"lamda": 0.02, "gamma": 0.001, "steps": 100}}, "user_id": 41, "data": {"latent_factors": ["White Balloon, The (Badkonake sefid) (1995)", "Man Facing Southeast (1986)", "Yojimbo (1961)", "Bad and the Beautiful, The (1952)", "Passage to India, A (1984)", "Diabolique (Les diaboliques) (1955)", "Pride and Prejudice (1995)", "Gladiator (1992)", "Decalogue, The (Dekalog) (1989)", "Hachiko: A Dog's Story (a.k.a. Hachi: A Dog's Tale) (2009)"], "top_favorites": ["Tron (1982)", "Blade Runner (1982)", "1984 (Nineteen Eighty-Four) (1984)", "Matrix, The (1999)", "Lolita (1997)", "Blues Brothers, The (1980)", "Phantom of the Paradise (1974)", "Sgt. Pepper's Lonely Hearts Club Band (1978)", "Pink Floyd: The Wall (1982)", "2001: A Space Odyssey (1968)"], "nearest_neighbours": ["Taxi Driver (1976)", "Pulp Fiction (1994)", "Shawshank Redemption, The (1994)", "Schindler's List (1993)", "Dances with Wolves (1990)", "North by Northwest (1959)", "Raging Bull (1980)", "Insider, The (1999)", "Toy Story 2 (1999)", "Dark Knight, The (2008)"]}, "timestamp": "2018-05-03 11:05:00"}