{"user_id": 52, "config": {"maxtrix_factorization": {"steps": 15, "gamma": 0.001, "lamda": 0.02}, "worker": {"nums_workers": 3, "nums_recommendations": 15}}, "data": {"top_favorites": ["Harry Potter and the Sorcerer's Stone (a.k.a. Harry Potter and the Philosopher's Stone) (2001)", "Crouching Tiger, Hidden Dragon (Wo hu cang long) (2000)", "Bridget Jones's Diary (2001)", "Billy Elliot (2000)", "Aim\u00e9e & Jaguar (1999)", "Great Expectations (1998)", "Harry Potter and the Goblet of Fire (2005)", "Harry Potter and the Order of the Phoenix (2007)", "Very Long Engagement, A (Un long dimanche de fian\u00e7ailles) (2004)", "Amelie (Fabuleux destin d'Am\u00e9lie Poulain, Le) (2001)", "Gia (1998)", "Harry Potter and the Prisoner of Azkaban (2004)", "Hours, The (2002)", "Chocolat (2000)", "Monty Python's The Meaning of Life (1983)"], "nearest_neighbours": ["Seven (a.k.a. Se7en) (1995)", "L\u00e9on: The Professional (a.k.a. The Professional) (L\u00e9on) (1994)", "Shawshank Redemption, The (1994)", "Forrest Gump (1994)", "Godfather, The (1972)", "Shining, The (1980)", "Stand by Me (1986)", "Back to the Future (1985)", "Matrix, The (1999)", "Ferris Bueller's Day Off (1986)", "Fight Club (1999)", "High Fidelity (2000)", "Snatch (2000)", "Donnie Darko (2001)", "Lost in Translation (2003)"], "latent_factors": ["Toy Story (1995)", "Heat (1995)", "American President, The (1995)", "Four Rooms (1995)", "Get Shorty (1995)", "Twelve Monkeys (a.k.a. 12 Monkeys) (1995)", "Babe (1995)", "Dead Man Walking (1995)", "Usual Suspects, The (1995)", "Mr. Holland's Opus (1995)", "Things to Do in Denver When You're Dead (1995)", "Nick of Time (1995)", "Broken Arrow (1996)", "City Hall (1996)", "Happy Gilmore (1996)"]}, "timestamp": "2018-04-27 17:07:23"}