{"data": {"latent_factors": ["Toy Story (1995)", "Heat (1995)", "Casino (1995)", "Sense and Sensibility (1995)", "Get Shorty (1995)", "Twelve Monkeys (a.k.a. 12 Monkeys) (1995)", "Babe (1995)", "Clueless (1995)", "Seven (a.k.a. Se7en) (1995)", "Usual Suspects, The (1995)"], "nearest_neighbours": ["Rear Window (1954)", "North by Northwest (1959)", "Casablanca (1942)", "Sunset Blvd. (a.k.a. Sunset Boulevard) (1950)", "Citizen Kane (1941)", "Hamlet (1996)", "On the Waterfront (1954)", "Last Picture Show, The (1971)", "Network (1976)", "What Ever Happened to Baby Jane? (1962)"], "top_favorites": ["Hard Day's Night, A (1964)", "Sleeper (1973)", "Killing Fields, The (1984)", "Being There (1979)", "All That Jazz (1979)", "M*A*S*H (a.k.a. MASH) (1970)", "Bonnie and Clyde (1967)", "Bananas (1971)", "Apartment, The (1960)", "Roger & Me (1989)"]}, "config": {"worker": {"nums_recommendations": 10, "nums_workers": 3}, "maxtrix_factorization": {"gamma": 0.001, "steps": 40, "lamda": 0.02}}, "timestamp": "2018-04-27 21:01:22", "user_id": 65}