{"timestamp": "2018-04-29 23:12:43", "user_id": 83, "config": {"worker": {"nums_recommendations": 10, "nums_workers": 3}, "maxtrix_factorization": {"gamma": 0.001, "lamda": 0.02, "steps": 1000}}, "data": {"nearest_neighbours": ["Twelve Monkeys (a.k.a. 12 Monkeys) (1995)", "Shawshank Redemption, The (1994)", "Lion King, The (1994)", "Schindler's List (1993)", "Aladdin (1992)", "Bad News Bears (2005)", "Pirates of the Caribbean: Dead Man's Chest (2006)", "Civil War, The (1990)", "Journey, The (El viaje) (1992)", "Inside Out (2015)"], "latent_factors": ["Grumpier Old Men (1995)", "Father of the Bride Part II (1995)", "Persuasion (1995)", "Shanghai Triad (Yao a yao yao dao waipo qiao) (1995)", "Twelve Monkeys (a.k.a. 12 Monkeys) (1995)", "Seven (a.k.a. Se7en) (1995)", "Usual Suspects, The (1995)", "Postman, The (Postino, Il) (1994)", "Things to Do in Denver When You're Dead (1995)", "Mary Reilly (1996)"], "top_favorites": ["Rain Man (1988)", "Boot, Das (Boat, The) (1981)", "Naked Gun: From the Files of Police Squad!, The (1988)", "Serpico (1973)", "Animal House (1978)", "Airplane! (1980)", "National Lampoon's Vacation (1983)", "Rushmore (1998)", "Ferris Bueller's Day Off (1986)", "Gattaca (1997)"]}}