{"timestamp": "2018-04-30 02:16:32", "user_id": 91, "config": {"worker": {"nums_recommendations": 10, "nums_workers": 3}, "maxtrix_factorization": {"gamma": 0.001, "lamda": 0.02, "steps": 1000}}, "data": {"nearest_neighbours": ["Silence of the Lambs, The (1991)", "Godfather, The (1972)", "Godfather: Part II, The (1974)", "American Beauty (1999)", "Fight Club (1999)", "Bridget Jones's Diary (2001)", "Kill Bill: Vol. 1 (2003)", "Battle Royale (Batoru rowaiaru) (2000)", "Shaun of the Dead (2004)", "Little Miss Sunshine (2006)"], "latent_factors": ["Casino (1995)", "Persuasion (1995)", "City of Lost Children, The (Cit\u00e9 des enfants perdus, La) (1995)", "Shanghai Triad (Yao a yao yao dao waipo qiao) (1995)", "Twelve Monkeys (a.k.a. 12 Monkeys) (1995)", "Cry, the Beloved Country (1995)", "Seven (a.k.a. Se7en) (1995)", "Usual Suspects, The (1995)", "Mis\u00e9rables, Les (1995)", "Hate (Haine, La) (1995)"], "top_favorites": ["Braveheart (1995)", "Truman Show, The (1998)", "Matrix, The (1999)", "Lord of the Rings: The Two Towers, The (2002)", "Toy Story (1995)", "Intouchables (2011)", "Monsters, Inc. (2001)", "Batman Begins (2005)", "Inception (2010)", "The Man from U.N.C.L.E. (2015)"]}}