{"data": {"nearest_neighbours": ["Usual Suspects, The (1995)", "Taxi Driver (1976)", "Pulp Fiction (1994)", "Shawshank Redemption, The (1994)", "Forrest Gump (1994)", "Schindler's List (1993)", "Terminator 2: Judgment Day (1991)", "Star Wars: Episode V - The Empire Strikes Back (1980)", "Star Wars: Episode VI - Return of the Jedi (1983)", "Star Trek: First Contact (1996)", "Face/Off (1997)", "Saving Private Ryan (1998)", "Producers, The (1968)", "Insider, The (1999)", "Green Mile, The (1999)", "Blazing Saddles (1974)", "Serpico (1973)", "Adaptation (2002)", "25th Hour (2002)", "Old School (2003)"], "top_favorites": ["Almost Famous (2000)", "Wag the Dog (1997)", "Lord of the Rings: The Fellowship of the Ring, The (2001)", "Lord of the Rings: The Return of the King, The (2003)", "State and Main (2000)", "Get Shorty (1995)", "Juno (2007)", "Lord of the Rings: The Two Towers, The (2002)", "Up (2009)", "Incredibles, The (2004)", "Toy Story 3 (2010)", "My Best Friend (Mon meilleur ami) (2006)", "Philadelphia Story, The (1940)", "Millions (2004)", "Royal Tenenbaums, The (2001)", "Rear Window (1954)", "Casablanca (1942)", "Butch Cassidy and the Sundance Kid (1969)", "Godfather, The (1972)", "Rain Man (1988)"], "latent_factors": ["Toy Story (1995)", "Jumanji (1995)", "Heat (1995)", "GoldenEye (1995)", "Nixon (1995)", "Casino (1995)", "Get Shorty (1995)", "Leaving Las Vegas (1995)", "Persuasion (1995)", "Twelve Monkeys (a.k.a. 12 Monkeys) (1995)", "Babe (1995)", "Dead Man Walking (1995)", "Clueless (1995)", "Seven (a.k.a. Se7en) (1995)", "Usual Suspects, The (1995)", "Mr. Holland's Opus (1995)", "Friday (1995)", "From Dusk Till Dawn (1996)", "Bottle Rocket (1996)", "Muppet Treasure Island (1996)"]}, "timestamp": "2018-04-27 18:13:41", "user_id": 93, "config": {"maxtrix_factorization": {"steps": 20, "gamma": 0.001, "lamda": 0.02}, "worker": {"nums_recommendations": 20, "nums_workers": 3}}}