{"config": {"worker": {"nums_workers": 3, "nums_recommendations": 10}, "maxtrix_factorization": {"lamda": 0.02, "gamma": 0.001, "steps": 100}}, "user_id": 98, "data": {"latent_factors": ["White Balloon, The (Badkonake sefid) (1995)", "Man Facing Southeast (1986)", "Yojimbo (1961)", "Lion in Winter, The (1968)", "Bad and the Beautiful, The (1952)", "Passage to India, A (1984)", "Diabolique (Les diaboliques) (1955)", "Gladiator (1992)", "Decalogue, The (Dekalog) (1989)", "Hachiko: A Dog's Story (a.k.a. Hachi: A Dog's Tale) (2009)"], "top_favorites": ["Ice Age: The Great Egg-Scapade (2016)", "Mummy, The (1999)", "Big Hero 6 (2014)", "Harry Potter and the Deathly Hallows: Part 1 (2010)", "Runaway Bride (1999)", "Mona Lisa Smile (2003)", "I'm No Angel (1933)", "Fifth Element, The (1997)", "My Best Friend's Wedding (1997)", "Pleasantville (1998)"], "nearest_neighbours": ["Taxi Driver (1976)", "Shawshank Redemption, The (1994)", "Schindler's List (1993)", "Ghost (1990)", "Fargo (1996)", "Rear Window (1954)", "North by Northwest (1959)", "Mary Poppins (1964)", "Willy Wonka & the Chocolate Factory (1971)", "Boogie Nights (1997)"]}, "timestamp": "2018-05-03 11:12:33"}